app/__init__.py
app/api.py
app/config.py
app/mixin.py
app/swagger.py
app/__pycache__/__init__.cpython-310.pyc
app/__pycache__/api.cpython-310.pyc
app/__pycache__/config.cpython-310.pyc
app/__pycache__/mixin.cpython-310.pyc
app/__pycache__/swagger.cpython-310.pyc
app/blueprints/__init__.py
app/blueprints/__pycache__/__init__.cpython-310.pyc
app/blueprints/assets/__init__.py
app/blueprints/assets/resources.py
app/blueprints/assets/__pycache__/__init__.cpython-310.pyc
app/blueprints/assets/__pycache__/resources.cpython-310.pyc
app/blueprints/auth/__init__.py
app/blueprints/auth/resources.py
app/blueprints/auth/__pycache__/__init__.cpython-310.pyc
app/blueprints/auth/__pycache__/resources.cpython-310.pyc
app/blueprints/breakdown/__init__.py
app/blueprints/breakdown/resources.py
app/blueprints/breakdown/__pycache__/__init__.cpython-310.pyc
app/blueprints/breakdown/__pycache__/resources.cpython-310.pyc
app/blueprints/comments/__init__.py
app/blueprints/comments/resources.py
app/blueprints/comments/__pycache__/__init__.cpython-310.pyc
app/blueprints/comments/__pycache__/resources.cpython-310.pyc
app/blueprints/crud/__init__.py
app/blueprints/crud/asset_instance.py
app/blueprints/crud/attachment_file.py
app/blueprints/crud/base.py
app/blueprints/crud/comments.py
app/blueprints/crud/custom_action.py
app/blueprints/crud/day_off.py
app/blueprints/crud/department.py
app/blueprints/crud/entity.py
app/blueprints/crud/entity_link.py
app/blueprints/crud/entity_type.py
app/blueprints/crud/event.py
app/blueprints/crud/file_status.py
app/blueprints/crud/metadata_descriptor.py
app/blueprints/crud/milestone.py
app/blueprints/crud/news.py
app/blueprints/crud/notification.py
app/blueprints/crud/organisation.py
app/blueprints/crud/output_file.py
app/blueprints/crud/output_type.py
app/blueprints/crud/person.py
app/blueprints/crud/playlist.py
app/blueprints/crud/preview_background_file.py
app/blueprints/crud/preview_file.py
app/blueprints/crud/project.py
production_lan-17.1.0.dist-info/LICENSE.txt
production_lan-17.1.0.dist-info/METADATA
production_lan-17.1.0.dist-info/WHEEL
production_lan-17.1.0.dist-info/top_level.txt
production_lan-17.1.0.dist-info/RECORD
