Metadata-Version: 2.1
Name: production-lan
Version: 17.1.0
Summary: It's a Python library for VFX project-based LAN deployment
Author: Hitech Enterprise
Classifier: Development Status :: 5 - Production/Stable
Classifier: Environment :: Web Environment
Classifier: Framework :: Flask
Classifier: Intended Audience :: Developers
Classifier: Programming Language :: Python :: 3.8
Classifier: Programming Language :: Python :: 3.9
Classifier: Programming Language :: Python :: 3.10
Classifier: Programming Language :: Python :: 3.11
Classifier: Programming Language :: Python :: Implementation :: CPython
Classifier: Programming Language :: Python :: Implementation :: PyPy
Classifier: Topic :: Multimedia :: Graphics
License-File: LICENSE.txt
Requires-Dist: babel (==2.12.1)
Requires-Dist: click (==8.1.6)
Requires-Dist: discord.py (==2.3.1)
Requires-Dist: email-validator (==2.0.0.post2)
Requires-Dist: ffmpeg-python (==0.2.0)
Requires-Dist: fido2 (==1.1.2)
Requires-Dist: flasgger (==0.9.7.1)
Requires-Dist: flask-bcrypt (==1.0.1)
Requires-Dist: flask-caching (==2.0.2)
Requires-Dist: flask-fixtures (==0.3.8)
Requires-Dist: flask-mail (==0.9.1)
Requires-Dist: flask-principal (==0.4.0)
Requires-Dist: flask-restful (==0.3.10)
Requires-Dist: flask-sqlalchemy (==3.0.5)
Requires-Dist: flask-fs2[s3,swift] (==0.7.17)
Requires-Dist: flask-jwt-extended (==4.5.2)
Requires-Dist: flask-migrate (==4.0.4)
Requires-Dist: flask-socketio (==5.3.4)
Requires-Dist: flask (==2.3.2)
Requires-Dist: gazu (==0.9.4)
Requires-Dist: gevent-websocket (==0.10.1)
Requires-Dist: gevent (==23.7.0)
Requires-Dist: gunicorn (==21.2.0)
Requires-Dist: isoweek (==1.3.3)
Requires-Dist: itsdangerous (==2.1.2)
Requires-Dist: Jinja2 (==3.1.2)
Requires-Dist: ldap3 (==2.9.1)
Requires-Dist: matterhook (==0.2)
Requires-Dist: meilisearch (==0.28.1)
Requires-Dist: OpenTimelineIO (==0.15.0)
Requires-Dist: pillow (==10.0.0)
Requires-Dist: psutil (==5.9.5)
Requires-Dist: psycopg2-binary (==2.9.6)
Requires-Dist: pygelf (==0.4.2)
Requires-Dist: pyotp (==2.8.0)
Requires-Dist: python-nomad (==2.0.0)
Requires-Dist: python-slugify (==8.0.1)
Requires-Dist: python-socketio (==5.8.0)
Requires-Dist: pytz (==2023.3)
Requires-Dist: redis (==4.6.0)
Requires-Dist: requests (==2.31.0)
Requires-Dist: rq (==1.15.1)
Requires-Dist: slackclient (==2.9.4)
Requires-Dist: sqlalchemy-utils (==0.41.1)
Requires-Dist: sqlalchemy (==2.0.19)
Requires-Dist: ua-parser (==0.18.0)
Requires-Dist: werkzeug (==2.3.6)
